whist_core/__init__.py
whist_core/cards/__init__.py
whist_core/cards/card.py
whist_core/cards/card_container.py
whist_core/error/__init__.py
whist_core/error/matcher_error.py
whist_core/error/player_error.py
whist_core/error/table_error.py
whist_core/game/__init__.py
whist_core/game/errors.py
whist_core/game/game.py
whist_core/game/hand.py
whist_core/game/legal_checker.py
whist_core/game/play_order.py
whist_core/game/player_at_table.py
whist_core/game/rubber.py
whist_core/game/trick.py
whist_core/game/warnings.py
whist_core/scoring/__init__.py
whist_core/scoring/elo.py
whist_core/scoring/score.py
whist_core/scoring/score_calculator.py
whist_core/scoring/score_card.py
whist_core/scoring/team.py
whist_core/session/__init__.py
whist_core/session/distribution.py
whist_core/session/matcher.py
whist_core/session/session.py
whist_core/session/table.py
whist_core/session/userlist.py
whist_core/user/__init__.py
whist_core/user/player.py
whist_core/user/status.py
whist_core/user/user.py
whist_core/util.py
whist_core-0.9.2.dist-info/LICENSE
whist_core-0.9.2.dist-info/METADATA
whist_core-0.9.2.dist-info/WHEEL
whist_core-0.9.2.dist-info/RECORD
