Metadata-Version: 2.1
Name: whist-core
Version: 0.9.2
Summary: Whist rules implementation
Home-page: https://github.com/Whist-Team/Whist-Core
License: MIT
Keywords: game,whist
Author: Whist-Team
Requires-Python: >=3.9,<4.0
Classifier: License :: OSI Approved :: MIT License
Classifier: Operating System :: OS Independent
Classifier: Programming Language :: Python :: 3
Classifier: Programming Language :: Python :: 3.9
Classifier: Programming Language :: Python :: 3.10
Classifier: Programming Language :: Python :: 3.11
Classifier: Programming Language :: Python :: 3.12
Requires-Dist: deprecation (>=2.1,<3.0)
Requires-Dist: pydantic (>=2.6,<3.0)
Project-URL: Bug Tracker, https://github.com/Whist-Team/Whist-Core/issues
Project-URL: Documentation, https://whist-core.readthedocs.io
Project-URL: Repository, https://github.com/Whist-Team/Whist-Core
